{
  "selectedTemplate": 1,
  "headings": {
    "work": "Experience",
    "projects": "Projects",
    "awards": "Awards",
    "education": "Education"
  },
  "basics": {
    "name": "Bhavya Dang",
    "email": "bhavya.dang1207@gmail.com",
    "website": "https://github.com/bhavya-dang",
    "location": {
      "address": "Delhi, India"
    }
  },
  "education": [
    {
      "location": "Noida",
      "startDate": "2021",
      "endDate": "2025",
      "institution": "Amity University",
      "studyType": "Bachelors in",
      "area": "Computer Science",
      "gpa": "8.25"
    }
  ],
  "work": [
    {
      "website": "",
      "highlights": [null]
    },
    {
      "highlights": [
        "Sustainable Discipleship is a platform designed to foster Christian community and spiritual growth by enabling users to create organizations and groups. Leaders and disciples can engage with the Holy Bible and other Christian texts. The platform includes distinct screens tailored for different roles and adheres to GDPR guidelines.",
        "Tech Stack: React, Material UI, MySQL (Knex ORM), Express and Vercel"
      ],
      "location": "Remote",
      "position": "Full-Time Trainee",
      "company": "D2I Technology",
      "startDate": "15 May, 2024",
      "endDate": "5 July, 2024"
    },
    {
      "highlights": [
        "Hosted and conducted own workshop on MEVN Stack",
        "Organized 4 major events back-to-back with an average audience of almost 150 participants and conducted successful workshops"
      ],
      "company": "ALiAS - Amity Linux Assistance Sapience",
      "position": "Active Volunteer",
      "location": "Delhi",
      "startDate": "2022",
      "endDate": "2024"
    },
    {
      "highlights": [
        "Built BrowserMingle, a chrome extension that connects you with people who are consuming similar content.",
        "Uses Pinecone vector database for similarity search and Supabase for edge functions and data storage",
        "React, Tailwind and DaisyUI for the frontend and Bun for the backend"
      ],
      "company": "Supabase Week X Hackathon",
      "startDate": "12 Dec, 2023",
      "endDate": "19 Dec, 2023",
      "location": "Remote"
    },
    {
      "highlights": [
        "Worked on form recognition system for hospitals in Uganda",
        "Tested and Validated several forms, making sure that they pass the criteria for the AutoCorrection and Clarity system"
      ],
      "company": "ByFornoTri Tech",
      "position": "SDE Intern",
      "location": "Remote",
      "startDate": "Apr 3, 2023",
      "endDate": "May 3, 2023"
    }
  ],
  "skills": [
    {
      "level": "Intermediate",
      "keywords": ["JavaScript", "Python"],
      "name": "Programming Languages"
    },
    {
      "keywords": [
        "Vue.js",
        "React.js",
        "Tailwind CSS",
        "Astro",
        "Next.js",
        "Nuxt.js"
      ],
      "name": "Frameworks"
    },
    {
      "keywords": [
        "MongoDB",
        "MySQL",
        "Firebase",
        "PostgreSQL",
        "Prisma (ORM)",
        "Knex (ORM)",
        "Supabase"
      ],
      "name": "Databases"
    },
    {
      "keywords": ["Figma", "Photoshop", "After Effects"],
      "name": "Design"
    }
  ],
  "projects": [
    {
      "keywords": [
        "React",
        "Tailwind",
        "DaisyUI",
        "Bun",
        "Supabase",
        "Pinecone"
      ],
      "name": "browser-mingle",
      "description": "A chrome extension that connects you with people who are consuming similar content.",
      "url": "https://github.com/bhavya-dang/browser-mingle"
    },
    {
      "keywords": ["React", "Tailwind", "DaisyUI", "D3.js"],
      "name": "D3Movie",
      "description": "A movie app that uses D3.js to visualize movie data. Built for movie enthusiasts and analysts.",
      "url": "https://d3-movie.vercel.app/"
    },
    {
      "name": "AniKo",
      "description": "A simple anime and manga search list.",
      "url": "https://ani-ko.netlify.app",
      "keywords": ["Node.js", "Vue", "GraphQL", "Tailwind"]
    },
    {
      "keywords": ["Node.js", "Vue", "MongoDB"],
      "name": "Shortly",
      "description": "A url shortener built with MEVN stack.",
      "url": "https://shortly-site.onrender.com/"
    },
    {
      "keywords": ["Discord.js", "Node.js"],
      "url": "https://github.com/bhavya-dang/RyujinBot",
      "description": "A multi-purpose discord bot used by more than 20 servers and over 143k members.",
      "name": "RyujinBot"
    }
  ],
  "awards": [
    {
      "title": "Gold Medal - Zonal Robotics Competition",
      "awarder": "Government, 2019"
    },
    {
      "title": "Silver Medal - SOF Computer Science Olympiad",
      "awarder": "SOF, 2019"
    },
    {
      "title": "Silver Medal - SOF English Olympiad",
      "awarder": "SOF, 2019"
    }
  ],
  "sections": [
    "templates",
    "profile",
    "education",
    "work",
    "skills",
    "projects",
    "awards"
  ]
}
